peeman/__init__.py
peeman/__version__.py
peeman/cli.py
peeman/errors.py
peeman/schema_converter.py
peeman/test_regex.py
peeman/utils.py
peeman/mock/__init__.py
peeman/mock/apiman_resolver.py
peeman/mock/fakemock_resolver.py
peeman/mock/mock.py
peeman/parser/__init__.py
peeman/parser/collection.py
peeman/parser/folder.py
peeman/parser/request.py
peeman/parser/requestitem.py
peeman/parser/response.py
peeman/spec/__init__.py
peeman/spec/operation.py
peeman/spec/plugins.py
peeman/spec/spec.py
Peeman-1.0.4.dist-info/METADATA
Peeman-1.0.4.dist-info/WHEEL
Peeman-1.0.4.dist-info/entry_points.txt
Peeman-1.0.4.dist-info/top_level.txt
Peeman-1.0.4.dist-info/RECORD
