Metadata-Version: 2.1
Name: Peeman
Version: 1.0.4
Summary: A Postman to OpenAPI spec converter with mocking facilities
Home-page: UNKNOWN
License: MIT
Keywords: api,openapi,rest,specification,oas,documentation
Platform: UNKNOWN
Classifier: Development Status :: 3 - Alpha
Classifier: Intended Audience :: Developers
Classifier: Topic :: Software Development :: Build Tools
Classifier: License :: OSI Approved :: MIT License
Classifier: Programming Language :: Python :: 3
Classifier: Programming Language :: Python :: 3.5
Classifier: Programming Language :: Python :: 3.6
Requires-Python: >=3.5
Requires-Dist: apispec (==3.1.0)
Requires-Dist: Click (==7.0)
Requires-Dist: jsonpath-rw (==1.4.0)
Requires-Dist: connexion (~=2.6)
Requires-Dist: swagger-ui-bundle (==0.0.6)
Requires-Dist: Faker (==2.0.4)
Requires-Dist: flask-cors (==3.0.8)
Requires-Dist: pyyaml (==5.3.1)
